wbia_pyflann-4.0.4.dist-info/RECORD
wbia_pyflann-4.0.4.dist-info/COPYING
wbia_pyflann-4.0.4.dist-info/top_level.txt
wbia_pyflann-4.0.4.dist-info/WHEEL
wbia_pyflann-4.0.4.dist-info/METADATA
wbia_pyflann.libs/liblz4-af1653fb.so.1.8.3
wbia_pyflann.libs/libgomp-a34b3233.so.1.0.0
pyflann/__main__.py
pyflann/_version.py
pyflann/index.py
pyflann/__init__.py
pyflann/flann_ctypes.py
pyflann/exceptions.py
pyflann/lib/libflann.so.4.0.4
pyflann/lib/libflann.so.4.0
pyflann/lib/libflann_s.a
pyflann/lib/libflann_cpp.so
pyflann/lib/libflann_cpp.so.4.0.4
pyflann/lib/libflann.so
pyflann/lib/libflann_cpp_s.a
pyflann/lib/libflann_cpp.so.4.0
